LICENSE
MANIFEST.in
README.md
setup.py
nextbv2/__init__.py
nextbv2/version.py
nextbv2.egg-info/PKG-INFO
nextbv2.egg-info/SOURCES.txt
nextbv2.egg-info/dependency_links.txt
nextbv2.egg-info/entry_points.txt
nextbv2.egg-info/requires.txt
nextbv2.egg-info/top_level.txt
nextbv2/configs/__init__.py
nextbv2/configs/binance_config.py
nextbv2/configs/db_config.py
nextbv2/libs/binance/__init__.py
nextbv2/libs/binance/apis.py
nextbv2/libs/cli/__init__.py
nextbv2/libs/cli/cli_trade_online.py
nextbv2/libs/cli/cli_trade_simulation.py
nextbv2/libs/cli/data_process.py
nextbv2/libs/cli/data_statics.py
nextbv2/libs/common/__init__.py
nextbv2/libs/common/common.py
nextbv2/libs/common/constant.py
nextbv2/libs/common/nextb_time.py
nextbv2/libs/db/__init__.py
nextbv2/libs/db/serialize.py
nextbv2/libs/db/sqlite_db.py
nextbv2/libs/logs/__init__.py
nextbv2/libs/logs/logging.conf
nextbv2/libs/logs/logs.py
nextbv2/libs/trade/__init__.py
nextbv2/libs/trade/trade_one.py
nextbv2/libs/trade/trade_two.py