Metadata-Version: 2.1
Name: nextbv2
Version: 2.2.7
Summary: 币安量化交易实验程序
Home-page: https://github.com/a232319779/nexbv2
Author: ddvv
Author-email: dadavivi512@gmail.com
License: MIT
Platform: UNKNOWN
Classifier: Programming Language :: Python :: 3
Classifier: License :: OSI Approved :: MIT License
Classifier: Operating System :: OS Independent
Requires-Python: >=3.6
License-File: LICENSE
